{"ongoing_trials": {}, "hyperparameters": {"space": [{"class_name": "Int", "config": {"name": "units", "default": null, "conditions": [], "min_value": 64, "max_value": 256, "step": 32, "sampling": "linear"}}, {"class_name": "Float", "config": {"name": "dropout", "default": 0.0, "conditions": [], "min_value": 0.0, "max_value": 0.5, "step": 0.1, "sampling": "linear"}}], "values": {"units": 64, "dropout": 0.0}}, "start_order": ["0", "1", "2", "3", "4"], "end_order": ["0", "1", "2", "3", "4"], "run_times": {"0": 1, "1": 1, "2": 1, "3": 1, "4": 1}, "retry_queue": [], "seed": 2506, "seed_state": 2516, "tried_so_far": ["945fab8a20f513e9bf911caa5626506d", "e07320234055b5a6eba622d55eff36db", "51dc5f2afb44914dd49a960e69860a16", "fd0cefb0f10a0fbf567e749f665a453e", "d08651e7efc821e59d7109894751779b"], "id_to_hash": {"0": "51dc5f2afb44914dd49a960e69860a16", "1": "945fab8a20f513e9bf911caa5626506d", "2": "fd0cefb0f10a0fbf567e749f665a453e", "3": "d08651e7efc821e59d7109894751779b", "4": "e07320234055b5a6eba622d55eff36db"}, "num_initial_points": null, "alpha": 0.0001, "beta": 2.6}